{"0": "Chat & Briefing UI", "1": "Desktop OS Shell", "2": "Meridian Insurance Domain (M1.T1)", "3": "Two-System Architecture", "4": "Runtime Apps & APIs", "5": "CoursePackage Schema", "6": "App Registry & Page Shell", "7": "Intro Onboarding", "8": "BigQuery App", "9": "Meeting Recording Player", "10": "Solver: setup", "11": "Sheets App", "12": "Wallpapers API", "13": "Persona Picker", "14": "Judge API (Grading)", "15": "Solver Session Creator", "16": "Upload-Session Script", "17": "Solver: read-wiki", "18": "Solver: list-personas", "19": "TaskBar", "20": "Solver: list-wiki", "21": "Solver: interview", "22": "Solver: read-brief", "23": "Root Layout", "24": "Download-Package Script", "25": "Solver: submit", "26": "PostCSS Config", "27": "Next.js Config", "28": "Tailwind Config", "29": "App Providers", "30": "Favicon Route", "31": "Chat API Entry", "32": "Desktop Icons", "33": "Persona Voice System", "34": "Misc (singleton)", "35": "Misc (singleton)", "36": "Misc (singleton)", "37": "Misc (singleton)"}